architile/__init__.py
architile/_core.py
architile/tiling.py
architile-0.1.0.dist-info/licenses/LICENSE
architile-0.1.0.dist-info/WHEEL
architile-0.1.0.dist-info/METADATA
architile-0.1.0.dist-info/RECORD
