Metadata-Version: 2.4
Name: architile
Version: 0.1.0
Summary: An implementation of all 11 regular and Archimedean tilings
Author: florez
Author-email: florez <florez@ethz.ch>
License-Expression: MIT
License-File: LICENSE
Requires-Dist: numpy>=2.3.5
Requires-Python: >=3.11
